[{"title":"Some book","imageUrl":"https://cdn.pixabay.com/photo/2016/03/09/15/21/glasses-1246611_1280.jpg","description":"Some Description","price":"0"},{"title":"New Product","imageUrl":"https://cdn.pixabay.com/photo/2016/03/09/15/21/glasses-1246611_1280.jpg","description":"Some Description","price":"0"},{"title":"New Product","imageUrl":"https://cdn.pixabay.com/photo/2016/03/09/15/21/glasses-1246611_1280.jpg","description":"Some Description","price":"0"},{"title":"New Product","imageUrl":"https://cdn.pixabay.com/photo/2016/03/09/15/21/glasses-1246611_1280.jpg","description":"Some Description","price":"Free"},{"title":"New Product","imageUrl":"https://cdn.pixabay.com/photo/2016/03/09/15/21/glasses-1246611_1280.jpg","description":"Some Description","price":"Free"},{"title":"New Book","imageUrl":"https://cdn.pixabay.com/photo/2016/03/09/15/21/glasses-1246611_1280.jpg","description":"Very interesting book!","price":"40"},{"title":"New Product","imageUrl":"https://cdn.pixabay.com/photo/2016/03/09/15/21/glasses-1246611_1280.jpg","description":"Some Description","price":0},{"title":"New TItle","imageUrl":"https://cdn.pixabay.com/photo/2016/03/09/15/21/glasses-1246611_1280.jpg","description":"The new beautiful product. It'll make you happy. Try it right now. It's something very interesting. This text just for test of layout. Must to put very long text for it. So... Let's try it...","price":0},{"title":"New Product","imageUrl":"https://cdn.pixabay.com/photo/2016/03/09/15/21/glasses-1246611_1280.jpg","description":"Some Description","price":0},{"title":"New Product","imageUrl":"https://cdn.pixabay.com/photo/2016/03/09/15/21/glasses-1246611_1280.jpg","description":"Some Description","price":0}]